transkribus_to_prima/__init__.py
transkribus_to_prima/cli.py
transkribus_to_prima/cli_coordinate_fixer.py
transkribus_to_prima/convert.py
transkribus_to_prima/set_dimensions_from_image.py
transkribus_to_prima-0.0.1.dist-info/METADATA
transkribus_to_prima-0.0.1.dist-info/WHEEL
transkribus_to_prima-0.0.1.dist-info/entry_points.txt
transkribus_to_prima-0.0.1.dist-info/top_level.txt
transkribus_to_prima-0.0.1.dist-info/RECORD
