Metadata-Version: 2.1
Name: transkribus-to-prima
Version: 0.0.1
Summary: UNKNOWN
Home-page: https://github.com/kba/transkribus-to-prima
Author: kba, bertsky
Author-email: unixprog@gmail.com
License: Apache License 2.0
Platform: UNKNOWN
Requires-Dist: lxml
Requires-Dist: click
